nwb_conversion_tools/__init__.py
nwb_conversion_tools/basedatainterface.py
nwb_conversion_tools/nwbconverter.py
nwb_conversion_tools/datainterfaces/__init__.py
nwb_conversion_tools/datainterfaces/behavior/__init__.py
nwb_conversion_tools/datainterfaces/behavior/movie/__init__.py
nwb_conversion_tools/datainterfaces/behavior/movie/movie_utils.py
nwb_conversion_tools/datainterfaces/behavior/movie/moviedatainterface.py
nwb_conversion_tools/datainterfaces/ecephys/__init__.py
nwb_conversion_tools/datainterfaces/ecephys/baselfpextractorinterface.py
nwb_conversion_tools/datainterfaces/ecephys/baserecordingextractorinterface.py
nwb_conversion_tools/datainterfaces/ecephys/basesortingextractorinterface.py
nwb_conversion_tools/datainterfaces/ecephys/axona/__init__.py
nwb_conversion_tools/datainterfaces/ecephys/axona/axonadatainterface.py
nwb_conversion_tools/datainterfaces/ecephys/blackrock/__init__.py
nwb_conversion_tools/datainterfaces/ecephys/blackrock/blackrockdatainterface.py
nwb_conversion_tools/datainterfaces/ecephys/blackrock/header_tools.py
nwb_conversion_tools/datainterfaces/ecephys/ced/__init__.py
nwb_conversion_tools/datainterfaces/ecephys/ced/ceddatainterface.py
nwb_conversion_tools/datainterfaces/ecephys/cellexplorer/__init__.py
nwb_conversion_tools/datainterfaces/ecephys/cellexplorer/cellexplorerdatainterface.py
nwb_conversion_tools/datainterfaces/ecephys/intan/__init__.py
nwb_conversion_tools/datainterfaces/ecephys/intan/intandatainterface.py
nwb_conversion_tools/datainterfaces/ecephys/kilosort/__init__.py
nwb_conversion_tools/datainterfaces/ecephys/kilosort/kilosortdatainterface.py
nwb_conversion_tools/datainterfaces/ecephys/neuralynx/__init__.py
nwb_conversion_tools/datainterfaces/ecephys/neuralynx/neuralynxdatainterface.py
nwb_conversion_tools/datainterfaces/ecephys/neuroscope/__init__.py
nwb_conversion_tools/datainterfaces/ecephys/neuroscope/neuroscope_utils.py
nwb_conversion_tools/datainterfaces/ecephys/neuroscope/neuroscopedatainterface.py
nwb_conversion_tools-0.11.38.dist-info/LICENSE
nwb_conversion_tools-0.11.38.dist-info/METADATA
nwb_conversion_tools-0.11.38.dist-info/WHEEL
nwb_conversion_tools-0.11.38.dist-info/entry_points.txt
nwb_conversion_tools-0.11.38.dist-info/top_level.txt
nwb_conversion_tools-0.11.38.dist-info/RECORD
