Metadata-Version: 2.1
Name: nwb-conversion-tools
Version: 0.11.38
Summary: Convert data from proprietary formats to NWB format.
Home-page: https://github.com/catalystneuro/nwb-conversion-tools
Author: Ben Dichter, Cody Baker, and Luiz Tauffer
Author-email: ben.dichter@gmail.com
License: UNKNOWN
Keywords: nwb
Platform: UNKNOWN
Requires-Python: >=3.7
Requires-Dist: pynwb (>=1.4.0)
Requires-Dist: hdmf (>=3.2.1)
Requires-Dist: h5py (>=2.10.0)
Requires-Dist: tqdm (>=4.60.0)
Requires-Dist: natsort (>=7.1.1)
Requires-Dist: PyYAML (>=5.4)
Requires-Dist: jsonschema (>=3.2.0)
Requires-Dist: psutil (>=5.8.0)
Requires-Dist: dandi (==0.39.6)
Requires-Dist: spikeextractors (>=0.9.10)
Requires-Dist: spikeinterface (>=0.94.0)
Requires-Dist: neo (>=0.9.0)
Requires-Dist: roiextractors (==0.4.17)
Requires-Dist: lxml (>=4.6.5)
Requires-Dist: scipy (>=1.4.1)
Requires-Dist: click
Requires-Dist: pyopenephys (>=1.1.2)
Requires-Dist: numpy (>=1.21.0) ; python_version < "3.8"
Requires-Dist: numpy (>=1.22.0) ; python_version >= "3.8"
Provides-Extra: docs
Requires-Dist: myst-parser (==0.13.5) ; extra == 'docs'
Requires-Dist: Jinja2 (<3.1) ; extra == 'docs'
Requires-Dist: sphinx (==3.5.1) ; extra == 'docs'
Requires-Dist: sphinx-rtd-theme (==0.5.1) ; extra == 'docs'
Requires-Dist: readthedocs-sphinx-search (==0.1.0rc3) ; extra == 'docs'
Requires-Dist: sphinx-toggleprompt (==0.2.0) ; extra == 'docs'
Requires-Dist: sphinx-copybutton (==0.5.0) ; extra == 'docs'
Provides-Extra: full
Requires-Dist: dandi (==0.39.6) ; extra == 'full'
Requires-Dist: pynwb (==2.1.0) ; extra == 'full'
Requires-Dist: hdmf (==3.3.2) ; extra == 'full'
Requires-Dist: tqdm (==4.60.0) ; extra == 'full'
Requires-Dist: natsort (==7.1.1) ; extra == 'full'
Requires-Dist: pandas (==1.2.3) ; extra == 'full'
Requires-Dist: hdf5storage (==0.1.18) ; extra == 'full'
Requires-Dist: scipy (>=1.4.1) ; extra == 'full'
Requires-Dist: h5py (>=2.10.0) ; extra == 'full'
Requires-Dist: PyYAML (==5.4) ; extra == 'full'
Requires-Dist: jsonschema (==3.2.0) ; extra == 'full'
Requires-Dist: psutil (==5.8.0) ; extra == 'full'
Requires-Dist: lxml (==4.9.1) ; extra == 'full'
Requires-Dist: opencv-python (==4.5.1.48) ; extra == 'full'
Requires-Dist: spikeextractors (==0.9.10) ; extra == 'full'
Requires-Dist: spikeinterface (>=0.94.0) ; extra == 'full'
Requires-Dist: neo (==0.10.2) ; extra == 'full'
Requires-Dist: roiextractors (==0.4.17) ; extra == 'full'
Requires-Dist: pyintan (==0.3.0) ; extra == 'full'
Requires-Dist: pyopenephys (==1.1.2) ; extra == 'full'
Requires-Dist: sonpy (>=1.7.1) ; extra == 'full'
Requires-Dist: tiffile (==2018.10.18) ; extra == 'full'
Requires-Dist: ndx-dandi-icephys (>=0.4.0) ; extra == 'full'
Requires-Dist: pillow (==9.1.1) ; extra == 'full'
Requires-Dist: scanimage-tiff-reader (==1.4.1) ; extra == 'full'
Requires-Dist: numpy (==1.21.0) ; (python_version < "3.8") and extra == 'full'
Requires-Dist: numpy (==1.22.0) ; (python_version >= "3.8") and extra == 'full'
Provides-Extra: test
Requires-Dist: pytest ; extra == 'test'
Requires-Dist: pytest-cov ; extra == 'test'
Requires-Dist: ndx-events (==0.2.0) ; extra == 'test'
Requires-Dist: parameterized (==0.8.1) ; extra == 'test'
Requires-Dist: ndx-dandi-icephys (>=0.4.0) ; extra == 'test'
